yoloimporter/__init__.py
yoloimporter/doit.py
yoloimporter-0.1.dist-info/METADATA
yoloimporter-0.1.dist-info/WHEEL
yoloimporter-0.1.dist-info/licenses/LICENSE.txt
yoloimporter-0.1.dist-info/RECORD
