Metadata-Version: 2.1
Name: yoloimporter
Version: 0.1
Summary: import directly from PyPI
Project-URL: Home, https://github.com/ucodery/yoloimporter
Author-email: Jeremiah Paige <ucodery@gmail.com>
License: Copyright (c) 2024, Jeremiah Paige
License-File: LICENSE.txt
Classifier: License :: OSI Approved :: BSD License
Requires-Dist: pip
